pykeybindmanager/__init__.py
pykeybindmanager/exceptions.py
pykeybindmanager/keys.py
pykeybindmanager/manager.py
pykeybindmanager/sound_player.py
pykeybindmanager/sounds/__init__.py
pykeybindmanager/sounds/doubleping.wav
pykeybindmanager/sounds/singleping.wav
pykeybindmanager-0.2.2.dist-info/licenses/LICENSE
pykeybindmanager-0.2.2.dist-info/METADATA
pykeybindmanager-0.2.2.dist-info/WHEEL
pykeybindmanager-0.2.2.dist-info/top_level.txt
pykeybindmanager-0.2.2.dist-info/RECORD
