Metadata-Version: 2.4
Name: pykeybindmanager
Version: 0.2.2
Summary: A simple Python module for listening to keyboard keybinds (single keys or combinations) with toggle, double-press, and hold support.
Author: Boris Djordjevic
License-Expression: MIT
Project-URL: Homepage, https://github.com/YOUR_USERNAME/pykeybindmanager
Project-URL: Bug Tracker, https://github.com/YOUR_USERNAME/pykeybindmanager/issues
Classifier: Development Status :: 4 - Beta
Classifier: Intended Audience :: Developers
Classifier: Operating System :: MacOS
Classifier: Operating System :: Microsoft :: Windows
Classifier: Operating System :: POSIX :: Linux
Classifier: Programming Language :: Python :: 3
Classifier: Programming Language :: Python :: 3.7
Classifier: Programming Language :: Python :: 3.8
Classifier: Programming Language :: Python :: 3.9
Classifier: Programming Language :: Python :: 3.10
Classifier: Programming Language :: Python :: 3.11
Classifier: Programming Language :: Python :: 3.12
Classifier: Topic :: Software Development :: Libraries :: Python Modules
Classifier: Topic :: Desktop Environment
Classifier: Topic :: Utilities
Requires-Python: >=3.7
License-File: LICENSE
Requires-Dist: pynput>=1.7.0
Dynamic: license-file
